{
    "m_gameSession": 29,
    "m_waveNumber": 4,
    "m_waveDifficulty": 2.3809561729431154,
    "m_waveSpawntime": 247.30345153808595,
    "m_waveSpawnDuration": 20.0,
    "m_waveMaxClearDuration": 0.0,
    "m_wavePauseDuration": 20.0,
    "m_adjustedDifficultyGM": 2.4333372116088869,
    "m_adjustedDifficultyBCI": 0.0,
    "m_adjustedDifficultyWeighted": 2.4333372116088869,
    "m_Pause": true,
    "m_waveClearDuration": 61.31434631347656,
    "m_damageDealtInCloseCombat": 0,
    "m_unneccessaryActions": 0,
    "m_actionFrequency": Infinity,
    "m_actionTimes": [],
    "m_failedActions": 0,
    "m_performance": 0.5550000071525574,
    "m_lostHP": 0,
    "m_healedHP": 0,
    "m_healedHPPause": 0,
    "m_lostHPPercentage": 0.0,
    "m_lostBuildingHP": 340,
    "m_lostBuildings": 0,
    "m_healedBuildingHP": 0,
    "m_healedBuildingHPPause": 0,
    "m_lostBuildingHPPercentage": 0.17000000178813935,
    "m_lostBuildingsPercentage": 0.0,
    "m_goldCollected": 0,
    "m_goldLost": 0,
    "m_goldProfit": 0,
    "m_boredom_GM": 0.02200000360608101,
    "m_frustration_GM": -0.70333331823349,
    "m_bciStats_eng": [],
    "m_bciStats_exc": [],
    "m_bciStats_foc": [],
    "m_bciStats_int": [],
    "m_bciStats_rel": [],
    "m_bciStats_str": [],
    "m_bciStats_Pause_eng": [],
    "m_bciStats_Pause_exc": [],
    "m_bciStats_Pause_foc": [],
    "m_bciStats_Pause_int": [],
    "m_bciStats_Pause_rel": [],
    "m_bciStats_Pause_str": [],
    "m_boredom_BCI": 0.0,
    "m_frustration_BCI": 0.0
}